anthropic_bedrock/__init__.py
anthropic_bedrock/_auth.py
anthropic_bedrock/_base_client.py
anthropic_bedrock/_client.py
anthropic_bedrock/_compat.py
anthropic_bedrock/_constants.py
anthropic_bedrock/_exceptions.py
anthropic_bedrock/_files.py
anthropic_bedrock/_legacy_response.py
anthropic_bedrock/_models.py
anthropic_bedrock/_qs.py
anthropic_bedrock/_resource.py
anthropic_bedrock/_response.py
anthropic_bedrock/_stream_decoder.py
anthropic_bedrock/_streaming.py
anthropic_bedrock/_tokenizers.py
anthropic_bedrock/_types.py
anthropic_bedrock/_version.py
anthropic_bedrock/py.typed
anthropic_bedrock/tokenizer.json
anthropic_bedrock/_utils/__init__.py
anthropic_bedrock/_utils/_logs.py
anthropic_bedrock/_utils/_proxy.py
anthropic_bedrock/_utils/_streams.py
anthropic_bedrock/_utils/_sync.py
anthropic_bedrock/_utils/_transform.py
anthropic_bedrock/_utils/_typing.py
anthropic_bedrock/_utils/_utils.py
anthropic_bedrock/lib/.keep
anthropic_bedrock/resources/__init__.py
anthropic_bedrock/resources/completions.py
anthropic_bedrock/types/__init__.py
anthropic_bedrock/types/completion.py
anthropic_bedrock/types/completion_create_params.py
anthropic_bedrock-0.7.0.dist-info/METADATA
anthropic_bedrock-0.7.0.dist-info/WHEEL
anthropic_bedrock-0.7.0.dist-info/licenses/LICENSE
anthropic_bedrock-0.7.0.dist-info/RECORD
