Metadata-Version: 2.1
Name: anthropic-bedrock
Version: 0.7.0
Summary: The official Python library for the anthropic-bedrock API
Project-URL: Homepage, https://github.com/anthropics/anthropic-bedrock-python
Project-URL: Repository, https://github.com/anthropics/anthropic-bedrock-python
Author-email: Anthropic Bedrock <dev-feedback@anthropic.com>
License-Expression: MIT
License-File: LICENSE
Classifier: Intended Audience :: Developers
Classifier: License :: OSI Approved :: MIT License
Classifier: Operating System :: MacOS
Classifier: Operating System :: Microsoft :: Windows
Classifier: Operating System :: OS Independent
Classifier: Operating System :: POSIX
Classifier: Operating System :: POSIX :: Linux
Classifier: Programming Language :: Python :: 3.7
Classifier: Programming Language :: Python :: 3.8
Classifier: Programming Language :: Python :: 3.9
Classifier: Programming Language :: Python :: 3.10
Classifier: Programming Language :: Python :: 3.11
Classifier: Programming Language :: Python :: 3.12
Classifier: Topic :: Software Development :: Libraries :: Python Modules
Classifier: Typing :: Typed
Requires-Python: >=3.7
Requires-Dist: anyio<5,>=3.5.0
Requires-Dist: boto3>=1.28.57
Requires-Dist: botocore>=1.31.57
Requires-Dist: cached-property; python_version < '3.8'
Requires-Dist: distro<2,>=1.7.0
Requires-Dist: httpx<1,>=0.23.0
Requires-Dist: pydantic<3,>=1.9.0
Requires-Dist: sniffio
Requires-Dist: tokenizers>=0.13.0
Requires-Dist: typing-extensions<5,>=4.7
